dbt/adapters/fabricspark/__init__.py
dbt/adapters/fabricspark/__version__.py
dbt/adapters/fabricspark/column.py
dbt/adapters/fabricspark/connections.py
dbt/adapters/fabricspark/credentials.py
dbt/adapters/fabricspark/impl.py
dbt/adapters/fabricspark/livysession.py
dbt/adapters/fabricspark/relation.py
dbt/adapters/fabricspark/shortcut.py
dbt/adapters/fabricspark/shortcuts.py
dbt/include/fabricspark/__init__.py
dbt/include/fabricspark/dbt_project.yml
dbt/include/fabricspark/profile_template.yml
dbt/include/fabricspark/macros/adapters.sql
dbt/include/fabricspark/macros/apply_grants.sql
dbt/include/fabricspark/macros/adapters/columns.sql
dbt/include/fabricspark/macros/adapters/relation.sql
dbt/include/fabricspark/macros/adapters/schema.sql
dbt/include/fabricspark/macros/materializations/test.sql
dbt/include/fabricspark/macros/materializations/models/incremental/column_helpers.sql
dbt/include/fabricspark/macros/materializations/models/incremental/incremental.sql
dbt/include/fabricspark/macros/materializations/models/incremental/strategies.sql
dbt/include/fabricspark/macros/materializations/models/incremental/validate.sql
dbt/include/fabricspark/macros/materializations/models/table/clone.sql
dbt/include/fabricspark/macros/materializations/models/table/create_table_as.sql
dbt/include/fabricspark/macros/materializations/models/table/table.sql
dbt/include/fabricspark/macros/materializations/models/view/create_view_as.sql
dbt/include/fabricspark/macros/materializations/models/view/mv.sql
dbt/include/fabricspark/macros/materializations/seeds/seed.sql
dbt/include/fabricspark/macros/materializations/snapshots/snapshot.sql
dbt/include/fabricspark/macros/utils/any_value.sql
dbt/include/fabricspark/macros/utils/array_append.sql
dbt/include/fabricspark/macros/utils/array_concat.sql
dbt/include/fabricspark/macros/utils/array_construct.sql
dbt/include/fabricspark/macros/utils/assert_not_null.sql
dbt/include/fabricspark/macros/utils/bool_or.sql
dbt_fabricspark-1.9.1.dist-info/METADATA
dbt_fabricspark-1.9.1.dist-info/WHEEL
dbt_fabricspark-1.9.1.dist-info/licenses/LICENSE
dbt_fabricspark-1.9.1.dist-info/RECORD
