Metadata-Version: 2.4
Name: dbt-fabricspark
Version: 1.9.1
Summary: A Microsoft Fabric Spark adapter plugin for dbt
Project-URL: homepage, https://github.com/microsoft/dbt-fabricspark
Project-URL: Setup & configuration, https://docs.getdbt.com/reference/warehouse-profiles/fabricspark-profile
Project-URL: Documentation & usage, https://docs.getdbt.com/reference/resource-configs/fabricspark-configs
Project-URL: Changelog, https://github.com/microsoft/dbt-fabricspark/releases
Project-URL: Issue Tracker, https://github.com/microsoft/dbt-fabricspark/issues
Author-email: Pradeep Srikakolapu <pvenkat@microsoft.com>
License-Expression: MIT
License-File: LICENSE
Keywords: Fabric lakehouse,adapter,adapters,database,dbt,dbt Cloud,dbt Core,dbt Labs,dbt-core,elt,fabric,fabricspark,fabricspark adapter,fabricspark dbt,fabricspark dbt adapter,fabricspark dbt adapters,fabricspark dbt cloud,fabricspark dbt core,fabricspark dbt labs,lakehouse,lakehouse dbt,lakehouse dbt adapter,lakehouse dbt adapters,lakehouse dbt cloud,lakehouse dbt core,lakehouse dbt labs,microsoft,spark
Classifier: Development Status :: 5 - Production/Stable
Classifier: Operating System :: MacOS :: MacOS X
Classifier: Operating System :: Microsoft :: Windows
Classifier: Operating System :: POSIX :: Linux
Classifier: Programming Language :: Python :: 3.9
Classifier: Programming Language :: Python :: 3.10
Classifier: Programming Language :: Python :: 3.11
Classifier: Programming Language :: Python :: 3.12
Classifier: Programming Language :: Python :: 3.13
Requires-Python: <3.14,>=3.9
Requires-Dist: dbt-adapters<2.0,>=1.7
Requires-Dist: dbt-common<2.0,>=1.10
Requires-Dist: dbt-core>=1.8.0
